MANIFEST.in
README.md
requirements.txt
setup.py
dotconfig/__init__.py
pydotconfig.egg-info/PKG-INFO
pydotconfig.egg-info/SOURCES.txt
pydotconfig.egg-info/dependency_links.txt
pydotconfig.egg-info/requires.txt
pydotconfig.egg-info/top_level.txt