Metadata-Version: 1.1
Name: pydotconfig
Version: 0.1.5
Summary: Super simple python module for parsing structured config files with overrides
Home-page: https://github.com/adammhaile/dotconfig
Author: UNKNOWN
Author-email: UNKNOWN
License: LGPL v3.0
Platform: UNKNOWN
Classifier: Development Status :: 5 - Production/Stable
Classifier: License :: OSI Approved :: GNU Lesser General Public License v3 (LGPLv3)
Classifier: Programming Language :: Python :: 2.7
